{
  "indexes": [
    {
      "collectionGroup": "messages",
      "queryScope": "COLLECTION",
      "fields": [
        {
          "fieldPath": "conversationId",
          "order": "ASCENDING"
        },
        {
          "fieldPath": "createdAt",
          "order": "ASCENDING"
        }
      ]
    },
    {
      "collectionGroup": "notifications",
      "queryScope": "COLLECTION",
      "fields": [
        {
          "fieldPath": "recipientId",
          "order": "ASCENDING"
        },
        {
          "fieldPath": "createdAt",
          "order": "DESCENDING"
        }
      ]
    },
    {
      "collectionGroup": "notifications",
      "queryScope": "COLLECTION",
      "fields": [
        {
          "fieldPath": "recipientId",
          "order": "ASCENDING"
        },
        {
          "fieldPath": "read",
          "order": "ASCENDING"
        }
      ]
    },
    {
      "collectionGroup": "activities",
      "queryScope": "COLLECTION",
      "fields": [
        {
          "fieldPath": "partnerId",
          "order": "ASCENDING"
        },
        {
          "fieldPath": "jobId",
          "order": "ASCENDING"
        },
        {
          "fieldPath": "createdAt",
          "order": "ASCENDING"
        }
      ]
    },
    {
      "collectionGroup": "activities",
      "queryScope": "COLLECTION",
      "fields": [
        {
          "fieldPath": "partnerId",
          "order": "ASCENDING"
        },
        {
          "fieldPath": "orderId",
          "order": "ASCENDING"
        },
        {
          "fieldPath": "createdAt",
          "order": "ASCENDING"
        }
      ]
    }
  ],
  "fieldOverrides": []
}
